{
  "id": "skilltree:blacksmith_defensive_crafting_keystone_1",
  "bonuses": [
    {
      "type": "skilltree:crafted_item_bonus",
      "item_condition": {
        "equipment_type": "armor",
        "type": "skilltree:equipment_type"
      },
      "item_bonus": {
        "skill_bonus": {
          "attribute": "minecraft:generic.armor",
          "id": "7289999c-47f1-4fc8-8ce5-d4ec50fb2570",
          "name": "SkillBonus",
          "amount": 1.0,
          "operation": 0,
          "player_multiplier": {
            "type": "skilltree:none"
          },
          "player_condition": {
            "type": "skilltree:none"
          },
          "type": "skilltree:attribute"
        },
        "type": "skilltree:skill_bonus"
      }
    }
  ],
  "directConnections": [],
  "longConnections": [],
  "oneWayConnections": [],
  "backgroundTexture": "skilltree:textures/icons/background/keystone.png",
  "iconTexture": "skilltree:textures/icons/blacksmith_defensive_crafting_keystone_1.png",
  "borderTexture": "skilltree:textures/tooltip/keystone.png",
  "titleColor": "",
  "positionX": -336.64246,
  "positionY": -87.01296,
  "buttonSize": 24,
  "isStartingPoint": false
}